historical/__about__.py
historical/__init__.py
historical/attributes.py
historical/cli.py
historical/constants.py
historical/models.py
historical/common/__init__.py
historical/common/accounts.py
historical/common/cloudwatch.py
historical/common/dynamodb.py
historical/common/exceptions.py
historical/common/extensions.py
historical/common/proxy.py
historical/common/sqs.py
historical/common/util.py
historical/mapping/__init__.py
historical/s3/__init__.py
historical/s3/collector.py
historical/s3/differ.py
historical/s3/models.py
historical/s3/poller.py
historical/security_group/__init__.py
historical/security_group/collector.py
historical/security_group/differ.py
historical/security_group/models.py
historical/security_group/poller.py
historical/tests/__init__.py
historical/tests/conftest.py
historical/tests/factories.py
historical/tests/pynamodb_settings.py
historical/tests/test_cloudwatch.py
historical/tests/test_commons.py
historical/tests/test_proxy.py
historical/tests/test_s3.py
historical/tests/test_security_group.py
historical/tests/test_vpc.py
historical/vpc/__init__.py
historical/vpc/collector.py
historical/vpc/differ.py
historical/vpc/models.py
historical/vpc/poller.py
historical-0.4.10.dist-info/DESCRIPTION.rst
historical-0.4.10.dist-info/METADATA
historical-0.4.10.dist-info/RECORD
historical-0.4.10.dist-info/WHEEL
historical-0.4.10.dist-info/entry_points.txt
historical-0.4.10.dist-info/metadata.json
historical-0.4.10.dist-info/top_level.txt
