Metadata-Version: 2.0
Name: historical
Version: 0.4.10
Summary: Historical tracking of AWS resource configuration.
Home-page: https://github.com/Netflix-Skunkworks/historical
Author: The Historical developers
Author-email: security@netflix.com
License: UNKNOWN
Keywords: aws,account_management
Platform: UNKNOWN
Classifier: Programming Language :: Python
Classifier: Programming Language :: Python :: 3
Classifier: Programming Language :: Python :: 3.6
Provides-Extra: tests
Requires-Dist: boto3 (>=1.9.47)
Requires-Dist: cloudaux (>=1.4.14)
Requires-Dist: click (>=6.7)
Requires-Dist: pynamodb (>=3.3.1)
Requires-Dist: deepdiff (>=3.3.0)
Requires-Dist: raven-python-lambda (>=0.1.7)
Requires-Dist: marshmallow (>=2.13.5)
Requires-Dist: swag-client (==0.4.3)
Requires-Dist: python-dateutil (==2.6.1)
Requires-Dist: Jinja2 (==2.10)
Provides-Extra: tests
Requires-Dist: cookiecutter (==1.6.0); extra == 'tests'
Requires-Dist: pytest (==3.1.3); extra == 'tests'
Requires-Dist: pytest-cov (>=2.5.1); extra == 'tests'
Requires-Dist: mock (==2.0.0); extra == 'tests'
Requires-Dist: moto (>=1.3.2); extra == 'tests'
Requires-Dist: coveralls (==1.1); extra == 'tests'
Requires-Dist: factory-boy (==2.9.2); extra == 'tests'
Requires-Dist: tox (==3.4.0); extra == 'tests'
